[
    {
        "uuid": "858211",
        "timestamp": "15.06.2025, 14:05:51"
    },
    {
        "uuid": "764952",
        "timestamp": "15.06.2025, 14:13:02"
    },
    {
        "uuid": "418397",
        "timestamp": "15.06.2025, 14:17:09"
    },
    {
        "uuid": "241984",
        "timestamp": "15.06.2025, 14:21:51"
    },
    {
        "uuid": "233074",
        "timestamp": "15.06.2025, 14:32:11"
    },
    {
        "uuid": "822065",
        "timestamp": "15.06.2025, 14:32:32"
    },
    {
        "uuid": "170956",
        "timestamp": "15.06.2025, 14:33:19"
    },
    {
        "uuid": "143022",
        "timestamp": "15.06.2025, 14:35:51"
    },
    {
        "uuid": "190610",
        "timestamp": "15.06.2025, 14:36:24"
    },
    {
        "uuid": "827031",
        "timestamp": "15.06.2025, 14:51:28"
    },
    {
        "uuid": "244702",
        "timestamp": "15.06.2025, 14:53:29"
    },
    {
        "uuid": "303022",
        "timestamp": "15.06.2025, 15:11:03"
    },
    {
        "uuid": "902883",
        "timestamp": "15.06.2025, 15:11:30"
    },
    {
        "uuid": "293724",
        "timestamp": "15.06.2025, 15:12:06"
    },
    {
        "uuid": "290077",
        "timestamp": "15.06.2025, 15:12:37"
    },
    {
        "uuid": "780269",
        "timestamp": "15.06.2025, 15:28:51"
    },
    {
        "uuid": "325760",
        "timestamp": "15.06.2025, 15:29:12"
    },
    {
        "uuid": "238400",
        "timestamp": "15.06.2025, 15:29:37"
    },
    {
        "uuid": "100221",
        "timestamp": "15.06.2025, 16:21:48"
    },
    {
        "uuid": "104150",
        "timestamp": "15.06.2025, 16:53:41"
    },
    {
        "uuid": "203332",
        "timestamp": "15.06.2025, 16:55:32"
    },
    {
        "uuid": "142308",
        "timestamp": "15.06.2025, 16:59:08"
    },
    {
        "uuid": "145604",
        "timestamp": "15.06.2025, 17:02:28"
    },
    {
        "uuid": "271359",
        "timestamp": "15.06.2025, 17:05:38"
    },
    {
        "uuid": "197895",
        "timestamp": "15.06.2025, 20:47:35"
    },
    {
        "uuid": "190486",
        "timestamp": "15.06.2025, 20:49:03"
    },
    {
        "uuid": "101612",
        "timestamp": "15.06.2025, 20:53:18"
    },
    {
        "uuid": "261607",
        "timestamp": "15.06.2025, 20:55:33"
    },
    {
        "uuid": "133907",
        "timestamp": "15.06.2025, 22:01:10"
    },
    {
        "uuid": "196885",
        "timestamp": "15.06.2025, 23:37:14"
    },
    {
        "uuid": "126953",
        "timestamp": "16.06.2025, 13:15:04"
    },
    {
        "uuid": "313772",
        "timestamp": "16.06.2025, 13:17:40"
    },
    {
        "uuid": "320200",
        "timestamp": "16.06.2025, 13:28:23"
    },
    {
        "uuid": "123591",
        "timestamp": "16.06.2025, 13:32:46"
    },
    {
        "uuid": "204665",
        "timestamp": "16.06.2025, 21:20:32"
    },
    {
        "uuid": "202443",
        "timestamp": "16.06.2025, 21:22:14"
    },
    {
        "uuid": "579530",
        "timestamp": "16.06.2025, 21:24:33"
    },
    {
        "uuid": "616168",
        "timestamp": "16.06.2025, 21:28:42"
    },
    {
        "uuid": "338267",
        "timestamp": "16.06.2025, 21:44:29"
    },
    {
        "uuid": "852832",
        "timestamp": "16.06.2025, 22:03:25"
    },
    {
        "uuid": "280478",
        "timestamp": "16.06.2025, 22:52:54"
    },
    {
        "uuid": "279911",
        "timestamp": "16.06.2025, 23:28:12"
    },
    {
        "uuid": "191680",
        "timestamp": "16.06.2025, 23:29:49"
    },
    {
        "uuid": "221742",
        "timestamp": "16.06.2025, 23:31:28"
    },
    {
        "uuid": "194257",
        "timestamp": "17.06.2025, 00:20:49"
    },
    {
        "uuid": "151716",
        "timestamp": "17.06.2025, 00:23:51"
    },
    {
        "uuid": "304442",
        "timestamp": "17.06.2025, 00:26:40"
    },
    {
        "uuid": "270968",
        "timestamp": "17.06.2025, 00:29:35"
    },
    {
        "uuid": "144459",
        "timestamp": "17.06.2025, 01:12:09"
    },
    {
        "uuid": "187440",
        "timestamp": "17.06.2025, 01:14:17"
    },
    {
        "uuid": "234060",
        "timestamp": "17.06.2025, 01:17:01"
    },
    {
        "uuid": "272374",
        "timestamp": "17.06.2025, 01:18:31"
    },
    {
        "uuid": "192415",
        "timestamp": "17.06.2025, 01:21:37"
    },
    {
        "uuid": "310338",
        "timestamp": "23.06.2025, 21:34:05"
    },
    {
        "uuid": "184609",
        "timestamp": "23.06.2025, 21:35:27"
    },
    {
        "uuid": "256923",
        "timestamp": "24.06.2025, 09:43:44"
    },
    {
        "uuid": "169126",
        "timestamp": "24.06.2025, 09:44:54"
    },
    {
        "uuid": "456111",
        "timestamp": "24.06.2025, 09:48:36"
    }
]